[
  {
    "id": "smoke_help",
    "enabled": true,
    "timeout_sec": 300,
    "risk": "smoke",
    "cmd": [
      "python",
      "run.py",
      "-h"
    ]
  },
  {
    "id": "install_requirements",
    "enabled": true,
    "timeout_sec": 1800,
    "risk": "heavy",
    "cmd": [
      "python",
      "-m",
      "pip",
      "install",
      "-r",
      "requirements.txt"
    ]
  },
  {
    "id": "prep_extract_dataset_setup",
    "enabled": true,
    "timeout_sec": 1200,
    "risk": "unknown",
    "cmd": [
      "cmd",
      "/c",
      "if exist preprocess.sh (bash preprocess.sh) else (echo preprocess.sh not found, skipping)"
    ]
  },
  {
    "id": "train_best_model_readme",
    "enabled": true,
    "timeout_sec": 86400,
    "risk": "heavy",
    "cmd": [
      "python",
      "run.py",
      "-name",
      "best_model",
      "-score_func",
      "conve",
      "-opn",
      "corr"
    ]
  },
  {
    "id": "train_transe_sub_readme",
    "enabled": true,
    "timeout_sec": 86400,
    "risk": "smoke",
    "cmd": [
      "python",
      "run.py",
      "-score_func",
      "transe",
      "-opn",
      "sub",
      "-gamma",
      "9",
      "-hid_drop",
      "0.1",
      "-init_dim",
      "200"
    ]
  }
]
